Workbook

Sheet Datos
C3: Para calculo de Depreciación | M3: Valor cuota y Tabla de Amortización
L5: Monto Prestamo | M5: 1095680
L6: Plazo | M6: 5 | N6: AÑOS
L7: Interes | M7: 0.08
L8: Cuota | M8: =PMT(M7,M6,M5) -> -274420.13
L11: Año | M11: Saldo | N11: Cuota | O11: Interes | P11: Amortizacion
L12: 1 | M12: =+M5 -> 1095680 | N12: =+$M$8*-1 -> 274420.13 | O12: =+M5*M7 -> 87654.4 | P12: =+N12-O12 -> 186765.73
L13: 2 | M13: =+M12-P12 -> 908914.27 | N13: =+$M$8*-1 -> 274420.13 | O13: =M13*$M$7 -> 72713.142 | P13: =+N13-O13 -> 201706.99
L14: 3 | M14: =+M13-P13 -> 707207.29 | N14: =+$M$8*-1 -> 274420.13 | O14: =M14*$M$7 -> 56576.583 | P14: =+N14-O14 -> 217843.55
L15: 4 | M15: =+M14-P14 -> 489363.74 | N15: =+$M$8*-1 -> 274420.13 | O15: =M15*$M$7 -> 39149.099 | P15: =+N15-O15 -> 235271.03
L16: 5 | M16: =+M15-P15 -> 254092.71 | N16: =+$M$8*-1 -> 274420.13 | O16: =M16*$M$7 -> 20327.417 | P16: =+N16-O16 -> 254092.71
B17: Tabla para calculo de Ganancia de Capital
L19: Calculo de Inversion | N19: Mts | O19: Precio | P19: Total
O20: US$ | P20: US$
L21: Hangar | N21: 1200 | O21: 36 | P21: =N21*O21 -> 43200
L22: Obras Fisicas | N22: 8000 | O22: 27 | P22: =N22*O22 -> 216000
L23: Equipo Instrumental | P23: 525000
L24: Equipo de Fuselaje | P24: 300000
L25: Terreno | N25: 10000 | O25: 48 | P25: =N25*O25 -> 480000
L26: Capital de Trabajo | P26: 1175000
M27: Total Inversion | P27: =SUM(P21:Q26) -> 2739200
B32: Demanda Estimada | G32: Costos | I32: Precio US$ | J32: TOTAL
B33: Mantenciones | D33: 900 | G33: Operacionales | I33: 8300 | J33: =I33*D33 -> 7470000
B34: Precio | D34: 12500 | G34: Mantencion | J34: 180000
B35: Total por Años | D35: =D33*D34 -> 11250000 | G35: Administración | J35: 25000
G36: Seguros | J36: 5000
B38: Impuesto | C38: 0.15

Sheet Proyecto Puro
C2: Flujo de Caja Proyecto Financiado
C4: ITEMS | E4: 0 | F4: 1 | G4: 2 | H4: 3 | I4: 4 | J4: 5
B5: + | C5: Ingresos | F5: =Datos!$D$35 -> 11250000 | G5: =Datos!$D$35 -> 11250000 | H5: =Datos!$D$35 -> 11250000 | I5: =Datos!$D$35 -> 11250000 | J5: =Datos!$D$35 -> 11250000
B6: - | C6: Costos Operacionales | F6: =-Datos!$J$33 -> -7470000 | G6: =-Datos!$J$33 -> -7470000 | H6: =-Datos!$J$33 -> -7470000 | I6: =-Datos!$J$33 -> -7470000 | J6: =-Datos!$J$33 -> -7470000
B7: - | C7: Costos de Mantención | F7: =-Datos!$J$34 -> -180000 | G7: =-Datos!$J$34 -> -180000 | H7: =-Datos!$J$34 -> -180000 | I7: =-Datos!$J$34 -> -180000 | J7: =-Datos!$J$34 -> -180000
B8: - | C8: Costos de Administración | F8: =-Datos!$J$35 -> -25000 | G8: =-Datos!$J$35 -> -25000 | H8: =-Datos!$J$35 -> -25000 | I8: =-Datos!$J$35 -> -25000 | J8: =-Datos!$J$35 -> -25000
B9: - | C9: Seguros | F9: =-Datos!$J$36 -> -5000 | G9: =-Datos!$J$36 -> -5000 | H9: =-Datos!$J$36 -> -5000 | I9: =-Datos!$J$36 -> -5000 | J9: =-Datos!$J$36 -> -5000
B10: - | C10: Depreciaciones
D11: Hangar | F11: -4320 | G11: -4320 | H11: -4320 | I11: -4320 | J11: -4320
D12: Obras Fisicas | F12: -21600 | G12: -21600 | H12: -21600 | I12: -21600 | J12: -21600
D13: Equipos Instrumental | F13: -105000 | G13: -105000 | H13: -105000 | I13: -105000 | J13: -105000
D14: Equipos de Fuselaje | F14: -60000 | G14: -60000 | H14: -60000 | I14: -60000 | J14: -60000
B15: + | C15: Ganancias de Capital | J15: 177720
B16: = | C16: Utilidad Antes de Impuesto | F16: =SUM(F5:F15) -> 3379080 | G16: =SUM(G5:G15) -> 3379080 | H16: =SUM(H5:H15) -> 3379080 | I16: =SUM(I5:I15) -> 3379080 | J16: =SUM(J5:J15) -> 3556800
B17: - | C17: Impuesto (15%) | F17: =-F16*Datos!$C$38 -> -506862 | G17: =-G16*Datos!$C$38 -> -506862 | H17: =-H16*Datos!$C$38 -> -506862 | I17: =-I16*Datos!$C$38 -> -506862 | J17: =-J16*Datos!$C$38 -> -533520
B18: = | C18: Utilidad después de Impuesto | F18: =SUM(F16:F17) -> 2872218 | G18: =SUM(G16:G17) -> 2872218 | H18: =SUM(H16:H17) -> 2872218 | I18: =SUM(I16:I17) -> 2872218 | J18: =SUM(J16:J17) -> 3023280
B19: + | C19: Depreciaciones
D20: Hangar | F20: =-F11 -> 4320 | G20: =-G11 -> 4320 | H20: =-H11 -> 4320 | I20: =-I11 -> 4320 | J20: =-J11 -> 4320
D21: Obras Fisicas | F21: =-F12 -> 21600 | G21: =-G12 -> 21600 | H21: =-H12 -> 21600 | I21: =-I12 -> 21600 | J21: =-J12 -> 21600
D22: Equipos Instrumental | F22: =-F13 -> 105000 | G22: =-G13 -> 105000 | H22: =-H13 -> 105000 | I22: =-I13 -> 105000 | J22: =-J13 -> 105000
D23: Equipos de Fuselaje | F23: =-F14 -> 60000 | G23: =-G14 -> 60000 | H23: =-H14 -> 60000 | I23: =-I14 -> 60000 | J23: =-J14 -> 60000
B24: + | C24: Ganancias de Capital | J24: =-J15 -> -177720
B25: - | C25: inversiones | E25: =-Datos!P27 -> -2739200
B26: + | C26: Recuperacion de Valores Residuales | J26: 1962320
B27: = | C27: Flujo de Caja Neto | E27: =SUM(E18:E26) -> -2739200 | F27: =SUM(F18:F26) -> 3063138 | G27: =SUM(G18:G26) -> 3063138 | H27: =SUM(H18:H26) -> 3063138 | I27: =SUM(I18:I26) -> 3063138 | J27: =SUM(J18:J26) -> 4998800
C28: Van (12%) | D28: =NPV(12%,F27:J27)+E27 -> 9401073.6

Sheet Proyecto Finaciado
C2: Flujo de Caja Proyecto Financiado
C4: ITEMS | E4: 0 | F4: 1 | G4: 2 | H4: 3 | I4: 4 | J4: 5
B5: + | C5: Ingresos | F5: 11250000.00 | G5: 11250000.00 | H5: 11250000.00 | I5: 11250000.00 | J5: 11250000.00
B6: - | C6: Costos Operacionales | F6: -7470000.00 | G6: -7470000.00 | H6: -7470000.00 | I6: -7470000.00 | J6: -7470000.00
B7: - | C7: Costos de Mantención | F7: -180000.00 | G7: -180000.00 | H7: -180000.00 | I7: -180000.00 | J7: -180000.00
B8: - | C8: Costos de Administración | F8: -25000.00 | G8: -25000.00 | H8: -25000.00 | I8: -25000.00 | J8: -25000.00
B9: - | C9: Seguros | F9: -5000.00 | G9: -5000.00 | H9: -5000.00 | I9: -5000.00 | J9: -5000.00
B10: - | C10: Gatos Finacieros | F10: -87654.40 | G10: -72713.14 | H10: -56576.58 | I10: -39149.10 | J10: -20327.42
B11: - | C11: Depreciaciones | F11: -190920.00 | G11: -190920.00 | H11: -190920.00 | I11: -190920.00 | J11: -190920.00
B12: + | C12: Ganancias de Capital | J12: 177720.00
B13: = | C13: Utilidad Antes de Impuesto | F13: 3291425.60 | G13: 3306366.86 | H13: 3322503.42 | I13: 3339930.90 | J13: 3536472.58
B14: - | C14: Impuesto (15%) | F14: -493713.84 | G14: -495955.03 | H14: -498375.51 | I14: -500989.64 | J14: -530470.89
B15: = | C15: Utilidad después de Impuesto | F15: 2797711.76 | G15: 2810411.83 | H15: 2824127.91 | I15: 2838941.26 | J15: 3006001.69
B16: + | C16: Depreciaciones | F16: 190920.00 | G16: 190920.00 | H16: 190920.00 | I16: 190920.00 | J16: 190920.00
B17: + | C17: Ganacia de Capital | J17: -177720.00
B18: + | C18: Préstamo | E18: 1095680.00
B19: - | C19: Amortizaciones | F19: -186765.73 | G19: -201706.99 | H19: -217843.55 | I19: -235271.03 | J19: -254092.71
B20: - | C20: inversiones | E20: -2739200.00
B21: + | C21: Recuperacion de Valores Residuales | J21: 1962320.00
B22: = | C22: Flujo de Caja Neto | E22: -1643520.00 | F22: 2801866.03 | G22: 2799624.84 | H22: 2797204.36 | I22: 2794590.23 | J22: 4727428.97
C23: Van (12%) | D23: 9540143.55
